betlib/__init__.py
betlib/bet_lib.py
betlib-0.1.2.5.dist-info/licenses/LICENSE
betlib-0.1.2.5.dist-info/METADATA
betlib-0.1.2.5.dist-info/WHEEL
betlib-0.1.2.5.dist-info/top_level.txt
betlib-0.1.2.5.dist-info/RECORD
